siguls_gui/mklittlefs
siguls_gui/mklittlefs.exe
siguls_gui/siguls_class.py
siguls_gui/siguls_gui_helper.py
siguls_gui/siguls_gui_helper.ui
siguls_gui/siguls_main.py
siguls_gui/siguls_resources.py
siguls_gui/siguls_resources.qrc
siguls_gui/ui_resources/128x128.png
siguls_gui/ui_resources/16x16.png
siguls_gui/ui_resources/24x24.png
siguls_gui/ui_resources/256x256.png
siguls_gui/ui_resources/32x32.png
siguls_gui/ui_resources/48x48.png
siguls_gui/ui_resources/64x64.png
siguls_gui/ui_resources/logo_dark.svg
siguls_gui-0.9.0.dist-info/METADATA
siguls_gui-0.9.0.dist-info/WHEEL
siguls_gui-0.9.0.dist-info/entry_points.txt
siguls_gui-0.9.0.dist-info/top_level.txt
siguls_gui-0.9.0.dist-info/RECORD
